{"id":"0f749c8a-4269-4748-9c2e-65bac6cef7c0","timestamp":1740728840429,"matcher":{"static":{},"wildcard":{},"dynamic":{}},"prerendered":["/","/tienda","/aviso-legal","/condiciones","/perfil","/dragones-custodio","/politica-de-cookies","/politica-de-privacidad","/coleccion","/temporada","/dia-a-dia","/equipo","/habitos","/login","/registro","/canjear-cupon","/canjear-cupon-oro","/eliminar-cuenta","/notificaciones","/crear-codigo-referido","/transfiere-plumas-a-hedera-previo2","/recordar-password-fin","/transfiere-plumas-a-hedera","/recordar-password-formulario","/vincular-codigo-referido","/vincular-wallet-hedera","/vincular-wallet-hedera-2","/sala-de-espera","/recordar-password","/transfiere-item-a-hedera","/transfiere-oro-a-hedera-previo2","/transfiere-oro-a-hedera-previo1","/transfiere-oro-a-hedera","/transfiere-plumas-a-hedera-previo1","/notificaciones-store"]}