{"id":"a1eb9206-196f-475d-9ff6-3d92610c016b","timestamp":1743905595683,"matcher":{"static":{},"wildcard":{},"dynamic":{}},"prerendered":["/","/temporada","/politica-de-cookies","/politica-de-privacidad","/aviso-legal","/tienda","/condiciones","/coleccion","/dia-a-dia","/dragones-custodio","/equipo","/habitos","/login","/registro","/canjear-cupon-oro","/eliminar-cuenta","/crear-codigo-referido","/canjear-cupon","/perfil","/recordar-password","/sala-de-espera","/transfiere-item-a-hedera","/recordar-password-formulario","/transfiere-oro-a-hedera","/transfiere-oro-a-hedera-previo2","/recordar-password-fin","/transfiere-oro-a-hedera-previo1","/notificaciones","/influye","/transfiere-plumas-a-hedera","/vincular-wallet-hedera","/vincular-wallet-hedera-2","/transfiere-plumas-a-hedera-previo2","/transfiere-plumas-a-hedera-previo1","/vincular-codigo-referido","/notificaciones-store"]}